README.md
setup.cfg
setup.py
cieloApi3Mon/__init__.py
cieloApi3Mon/address.py
cieloApi3Mon/cieloEcommerce.py
cieloApi3Mon/creditCard.py
cieloApi3Mon/customer.py
cieloApi3Mon/environment.py
cieloApi3Mon/merchant.py
cieloApi3Mon/objectJSON.py
cieloApi3Mon/payment.py
cieloApi3Mon/paymentfacilitator.py
cieloApi3Mon/recurrentPayment.py
cieloApi3Mon/sale.py
cieloApi3Mon/subestablishment.py
cieloApi3Mon.egg-info/PKG-INFO
cieloApi3Mon.egg-info/SOURCES.txt
cieloApi3Mon.egg-info/dependency_links.txt
cieloApi3Mon.egg-info/requires.txt
cieloApi3Mon.egg-info/top_level.txt
cieloApi3Mon/request/__init__.py
cieloApi3Mon/request/base.py
cieloApi3Mon/request/createCardToken.py
cieloApi3Mon/request/createSale.py
cieloApi3Mon/request/deactivateRecorrency.py
cieloApi3Mon/request/queryRecorrency.py
cieloApi3Mon/request/querySale.py
cieloApi3Mon/request/reactivateRecorrency.py
cieloApi3Mon/request/updateSale.py